{"document_instrument_name": "Processes, plans and strategies|Governance", "document_framework_name": [], "document_region_code": "Europe & Central Asia", "document_country_english_shortname": "Kyrgyzstan", "document_category": "Law", "document_sector_name": "Energy", "document_date": "07/07/1998", "document_language": "English", "document_name": "Law no. 88 'On energy saving'", "document_country_code": "KGZ", "document_hazard_name": [], "document_keyword": "Energy Demand", "document_response_name": "Mitigation", "document_url": "https://cdn.climatepolicyradar.org/KGZ/1998/KGZ-1998-07-07-Law no. 88 'On energy saving'_5800c67191f1b9d7b8cae3b253bf4b6f.pdf", "document_type": "Law", "text_blocks": [], "document_description": "This law determines objectives of energy savings and efficiency, and defines a legal and regulatory framework accordingly. It covers the sectors of production, conversion, transfer, storage, distribution and use of fuel and energy resources, in the corporate, private and public spheres (art. 2)."}