{"document_instrument_name": ["Capacity building|Governance", "Standards, obligations and norms|Regulation"], "document_framework_name": [], "document_region_code": "Europe & Central Asia", "document_country_english_shortname": "France", "document_category": "Policy", "document_sector_name": "Transportation", "document_date": "06/09/2020", "document_language": "English", "document_name": "Aeronautic sector support plan 2020", "document_country_code": "FRA", "document_hazard_name": [], "document_keyword": ["Transportation", "Covid19", "Stimulus Plan"], "document_response_name": "Mitigation", "document_url": "https://cdn.climatepolicyradar.org/FRA/2020/FRA-2020-09-06-Aeronautic sector support plan 2020_a4330e3f5fba733487651185187af32d.pdf", "document_type": "Plan", "text_blocks": [], "document_description": "This plan aims to support the French aeronautics industry hit by the COVID crisis with a total of 15 billion euros in aid, investment, loans and guarantees.&nbsp;The aeronautics industry is committed to carrying out profound transformations in favour of ecological transition."}