{"document_instrument_name": ["Processes, plans and strategies|Governance", "Institutional mandates|Governance"], "document_framework_name": [], "document_region_code": "Latin America & Caribbean", "document_country_english_shortname": "Costa Rica", "document_category": "Policy", "document_sector_name": "Economy-wide", "document_date": "08/07/2017", "document_language": "English", "document_name": "Executive Decree no 40615 creating the Scientific Council on Climate Change", "document_country_code": "CRI", "document_hazard_name": [], "document_keyword": "Institutions / Administrative Arrangements", "document_response_name": ["Mitigation", "Adaptation"], "document_url": "https://www.pgrweb.go.cr/scij/Busqueda/Normativa/Normas/nrm_texto_completo.aspx?param1=NRTC&nValor1=1&nValor2=84845&nValor3=109604&strTipM=TC", "document_type": "Decree", "text_blocks": [], "document_description": "This decree creates the Scientific Council on Climate Change. The Council is part of the Directrate for Climate Change of the Ministry for the Environment and Energy (MINAE). The Council is in charge of informing the Ministry on the specific topics needed (art. 2)."}