{"document_instrument_name": ["Education, training and knowledge dissemination|Information", "Processes, plans and strategies|Governance", "Capacity building|Governance", "Standards, obligations and norms|Regulation"], "document_framework_name": [], "document_region_code": "East Asia & Pacific", "document_country_english_shortname": "Indonesia", "document_category": "Law", "document_sector_name": ["Other", "Environment"], "document_date": "01/01/2009", "document_language": "Indonesian", "document_name": "Law of the Republic of Indonesia Number 31 of 2009 concerning Meteorology, Climatology, and Geophysics", "document_country_code": "IDN", "document_hazard_name": [], "document_keyword": [], "document_response_name": "Adaptation", "document_url": "https://cdn.climatepolicyradar.org/IDN/2009/IDN-2009-01-01-Law of the Republic of Indonesia Number 31 of 2009 concerning Meteorology, Climatology, and Geophysics_236fb594225f3bcd5247bd7b4c36b07d.pdf", "document_type": "Law", "text_blocks": [], "document_description": "The law on Meteorology, Climatology and Geophysics establishes the framework of the organisation of meteorology, climatology and geophysics to protect national interests in order to increase security and resilience to climate change."}