{"document_instrument_name": "Capacity building|Governance", "document_framework_name": [], "document_region_code": "Latin America & Caribbean", "document_country_english_shortname": "Chile", "document_category": "Policy", "document_sector_name": ["Transportation", "Energy"], "document_date": "12/01/2017", "document_language": "English", "document_name": "Climate Change Mitigation Plan for the Energy Sector", "document_country_code": "CHL", "document_hazard_name": [], "document_keyword": ["Energy Supply", "Energy Demand"], "document_response_name": ["Mitigation", "Adaptation"], "document_url": "https://cdn.climatepolicyradar.org/CHL/2017/CHL-2017-01-12-Climate Change Mitigation Plan for the Energy Sector_81cec1160140630d3ddcb3347e880294.pdf", "document_type": "Plan", "text_blocks": [], "document_description": "The Plan elaborates scenarios and establishes targets of specific reduction of greenhouse gases emissions within the energy sector. The Plan further promotes the incorporation of renewable energies in the country's energy matrix, and energy efficiency.<br />\n<br />\nThe government also published a <a href=\"http://www.precioalcarbonochile.cl/wp-content/uploads/2017/11/Lanzamiento-Consulta-Plan-de-Adaptación-2017-1.pdf\">draft adaptation plan for the energy sector.</a>"}