{"document_instrument_name": ["Research & Development, knowledge generation|Information", "Capacity building|Governance", "Nature based solutions and ecosystem restoration|Direct Investment"], "document_framework_name": [], "document_region_code": "Latin America & Caribbean", "document_country_english_shortname": "Chile", "document_category": "Policy", "document_sector_name": ["Economy-wide", "Disaster Risk Management (Drm)", "Adaptation"], "document_date": "07/05/2021", "document_language": "English", "document_name": "National Policy of Land Management (PNOT)", "document_country_code": "CHL", "document_hazard_name": [], "document_keyword": "Planning", "document_response_name": ["Mitigation", "Disaster Risk Management", "Adaptation"], "document_url": "https://cdn.climatepolicyradar.org/CHL/2021/CHL-2021-05-07-National Policy of Land Management (PNOT)_85902ee095012a0eab5a97d74e77cc4c.pdf", "document_type": "Policy", "text_blocks": [], "document_description": "This policy was prepared in 2019 and approved by a ministerial decree published in July 2021.&nbsp;<br><br>Objective 1.2 of the policy is to promote the occupation and development of the territory in a safe and resilient way that contributes to disaster risk reduction and adaptation to climate change.<br><br>Guideline 1.2.c states that management tools and mechanisms in land use planning that reduce disaster risk, increase resilience and consider adaptation to climate change by human settlements and strategic infrastructure must be considered.&nbsp;<br><br>Guideline 1.2.d commands to incorporate the functions of natural systems as tools for mitigating threats and adapting to climate change, in order to reduce the risk of disasters that may affect the lives and health of people, infrastructure, services, or the environment.<br><br>Guideline 3.1.d promotes public and private investment in all types of infrastructure, and the generation of knowledge that contributes to the sustainable use of critical natural resources, such as water, renewable energies and soils."}