{"document_instrument_name": "Tax incentives|Economic", "document_framework_name": [], "document_region_code": "Europe & Central Asia", "document_country_english_shortname": "United Kingdom", "document_category": "Law", "document_sector_name": [], "document_date": "25/12/2002", "document_language": "English", "document_name": "Preferential Tax Regimes for Biofuels", "document_country_code": "GBR", "document_hazard_name": [], "document_keyword": "Transportation", "document_response_name": "Mitigation", "document_url": "https://www.iea.org/policiesandmeasures/pams/unitedkingdom/name-22451-en.php(11/09/2017)", "document_type": "Law", "text_blocks": [], "document_description": "A reduced excise duty rate was introduced for biodiesel in July 2002 and bio-ethanol in 2005. Producers of bio-blend and bio-ethanol blend will also benefit from the reduced rate of excise duty, as the proportion of biodiesel or bio-ethanol in the blend bears the lower rate of excise duty."}